[{"code":"33.01","name":"Kabupaten Cilacap","level":"kabupaten"},{"code":"33.02","name":"Kabupaten Banyumas","level":"kabupaten"},{"code":"33.03","name":"Kabupaten Purbalingga","level":"kabupaten"},{"code":"33.04","name":"Kabupaten Banjarnegara","level":"kabupaten"},{"code":"33.05","name":"Kabupaten Kebumen","level":"kabupaten"},{"code":"33.06","name":"Kabupaten Purworejo","level":"kabupaten"},{"code":"33.07","name":"Kabupaten Wonosobo","level":"kabupaten"},{"code":"33.08","name":"Kabupaten Magelang","level":"kabupaten"},{"code":"33.09","name":"Kabupaten Boyolali","level":"kabupaten"},{"code":"33.10","name":"Kabupaten Klaten","level":"kabupaten"},{"code":"33.11","name":"Kabupaten Sukoharjo","level":"kabupaten"},{"code":"33.12","name":"Kabupaten Wonogiri","level":"kabupaten"},{"code":"33.13","name":"Kabupaten Karanganyar","level":"kabupaten"},{"code":"33.14","name":"Kabupaten Sragen","level":"kabupaten"},{"code":"33.15","name":"Kabupaten Grobogan","level":"kabupaten"},{"code":"33.16","name":"Kabupaten Blora","level":"kabupaten"},{"code":"33.17","name":"Kabupaten Rembang","level":"kabupaten"},{"code":"33.18","name":"Kabupaten Pati","level":"kabupaten"},{"code":"33.19","name":"Kabupaten Kudus","level":"kabupaten"},{"code":"33.20","name":"Kabupaten Jepara","level":"kabupaten"},{"code":"33.21","name":"Kabupaten Demak","level":"kabupaten"},{"code":"33.22","name":"Kabupaten Semarang","level":"kabupaten"},{"code":"33.23","name":"Kabupaten Temanggung","level":"kabupaten"},{"code":"33.24","name":"Kabupaten Kendal","level":"kabupaten"},{"code":"33.25","name":"Kabupaten Batang","level":"kabupaten"},{"code":"33.26","name":"Kabupaten Pekalongan","level":"kabupaten"},{"code":"33.27","name":"Kabupaten Pemalang","level":"kabupaten"},{"code":"33.28","name":"Kabupaten Tegal","level":"kabupaten"},{"code":"33.29","name":"Kabupaten Brebes","level":"kabupaten"},{"code":"33.71","name":"Kota Magelang","level":"kabupaten"},{"code":"33.72","name":"Kota Surakarta","level":"kabupaten"},{"code":"33.73","name":"Kota Salatiga","level":"kabupaten"},{"code":"33.74","name":"Kota Semarang","level":"kabupaten"},{"code":"33.75","name":"Kota Pekalongan","level":"kabupaten"},{"code":"33.76","name":"Kota Tegal","level":"kabupaten"}]