[{"code":"35.16.01","name":"Jatirejo","level":"kecamatan"},{"code":"35.16.02","name":"Gondang","level":"kecamatan"},{"code":"35.16.03","name":"Pacet","level":"kecamatan"},{"code":"35.16.04","name":"Trawas","level":"kecamatan"},{"code":"35.16.05","name":"Ngoro","level":"kecamatan"},{"code":"35.16.06","name":"Pungging","level":"kecamatan"},{"code":"35.16.07","name":"Kutorejo","level":"kecamatan"},{"code":"35.16.08","name":"Mojosari","level":"kecamatan"},{"code":"35.16.09","name":"Dlanggu","level":"kecamatan"},{"code":"35.16.10","name":"Bangsal","level":"kecamatan"},{"code":"35.16.11","name":"Puri","level":"kecamatan"},{"code":"35.16.12","name":"Trowulan","level":"kecamatan"},{"code":"35.16.13","name":"Sooko","level":"kecamatan"},{"code":"35.16.14","name":"Gedeg","level":"kecamatan"},{"code":"35.16.15","name":"Kemlagi","level":"kecamatan"},{"code":"35.16.16","name":"Jetis","level":"kecamatan"},{"code":"35.16.17","name":"Dawarblandong","level":"kecamatan"},{"code":"35.16.18","name":"Mojoanyar","level":"kecamatan"}]