[{"code":"11.14.01","name":"Teunom","level":"kecamatan"},{"code":"11.14.02","name":"Krueng Sabee","level":"kecamatan"},{"code":"11.14.03","name":"Setia Bakti","level":"kecamatan"},{"code":"11.14.04","name":"Sampoi Niet","level":"kecamatan"},{"code":"11.14.05","name":"Jaya","level":"kecamatan"},{"code":"11.14.06","name":"Panga","level":"kecamatan"},{"code":"11.14.07","name":"Indra Jaya","level":"kecamatan"},{"code":"11.14.08","name":"Darul Hikmah","level":"kecamatan"},{"code":"11.14.09","name":"Pasie Raya","level":"kecamatan"}]