[{"code":"36.04.05","name":"Kramatwatu","level":"kecamatan"},{"code":"36.04.06","name":"Waringinkurung","level":"kecamatan"},{"code":"36.04.07","name":"Bojonegara","level":"kecamatan"},{"code":"36.04.08","name":"Pulo Ampel","level":"kecamatan"},{"code":"36.04.09","name":"Ciruas","level":"kecamatan"},{"code":"36.04.11","name":"Kragilan","level":"kecamatan"},{"code":"36.04.12","name":"Pontang","level":"kecamatan"},{"code":"36.04.13","name":"Tirtayasa","level":"kecamatan"},{"code":"36.04.14","name":"Tanara","level":"kecamatan"},{"code":"36.04.15","name":"Cikande","level":"kecamatan"},{"code":"36.04.16","name":"Kibin","level":"kecamatan"},{"code":"36.04.17","name":"Carenang","level":"kecamatan"},{"code":"36.04.18","name":"Binuang","level":"kecamatan"},{"code":"36.04.19","name":"Petir","level":"kecamatan"},{"code":"36.04.20","name":"Tunjung Teja","level":"kecamatan"},{"code":"36.04.22","name":"Baros","level":"kecamatan"},{"code":"36.04.23","name":"Cikeusal","level":"kecamatan"},{"code":"36.04.24","name":"Pamarayan","level":"kecamatan"},{"code":"36.04.25","name":"Kopo","level":"kecamatan"},{"code":"36.04.26","name":"Jawilan","level":"kecamatan"},{"code":"36.04.27","name":"Ciomas","level":"kecamatan"},{"code":"36.04.28","name":"Pabuaran","level":"kecamatan"},{"code":"36.04.29","name":"Padarincang","level":"kecamatan"},{"code":"36.04.30","name":"Anyar","level":"kecamatan"},{"code":"36.04.31","name":"Cinangka","level":"kecamatan"},{"code":"36.04.32","name":"Mancak","level":"kecamatan"},{"code":"36.04.33","name":"Gunungsari","level":"kecamatan"},{"code":"36.04.34","name":"Bandung","level":"kecamatan"},{"code":"36.04.35","name":"Lebak Wangi","level":"kecamatan"}]