[{"code":"53.18.11.2001","name":"Wailangira","level":"kelurahan"},{"code":"53.18.11.2002","name":"Kahale","level":"kelurahan"},{"code":"53.18.11.2003","name":"Waikarara","level":"kelurahan"},{"code":"53.18.11.2004","name":"Panenggo Ede","level":"kelurahan"},{"code":"53.18.11.2005","name":"Waiha","level":"kelurahan"},{"code":"53.18.11.2006","name":"Wainyapu","level":"kelurahan"},{"code":"53.18.11.2007","name":"Loko Tali","level":"kelurahan"},{"code":"53.18.11.2008","name":"Waipakolo","level":"kelurahan"}]