[{"code":"94.02.04.2001","name":"Mewoluk","level":"kelurahan"},{"code":"94.02.04.2002","name":"Gumbru","level":"kelurahan"},{"code":"94.02.04.2003","name":"Anggulobaga","level":"kelurahan"},{"code":"94.02.04.2004","name":"Balinggup","level":"kelurahan"},{"code":"94.02.04.2005","name":"Waliba","level":"kelurahan"},{"code":"94.02.04.2006","name":"Nggininik","level":"kelurahan"},{"code":"94.02.04.2007","name":"Biak","level":"kelurahan"},{"code":"94.02.04.2008","name":"Wutikme","level":"kelurahan"}]