[{"code":"74.07.07.1001","name":"Patipelong","level":"kelurahan"},{"code":"74.07.07.1002","name":"Tongano Barat","level":"kelurahan"},{"code":"74.07.07.1003","name":"Bahari","level":"kelurahan"},{"code":"74.07.07.1004","name":"Tongano Timur","level":"kelurahan"},{"code":"74.07.07.2005","name":"Timu","level":"kelurahan"},{"code":"74.07.07.2006","name":"Dete","level":"kelurahan"},{"code":"74.07.07.2007","name":"Kulati","level":"kelurahan"},{"code":"74.07.07.2008","name":"Wawaotimu","level":"kelurahan"},{"code":"74.07.07.2009","name":"Kahiyanga","level":"kelurahan"}]