[{"code":"94.05.05.2001","name":"Pogoma","level":"kelurahan"},{"code":"94.05.05.2002","name":"Gagama","level":"kelurahan"},{"code":"94.05.05.2003","name":"Wiha","level":"kelurahan"},{"code":"94.05.05.2004","name":"Wakme","level":"kelurahan"},{"code":"94.05.05.2005","name":"Ugutmu","level":"kelurahan"},{"code":"94.05.05.2006","name":"Yugume","level":"kelurahan"},{"code":"94.05.05.2007","name":"Kolamagi","level":"kelurahan"},{"code":"94.05.05.2008","name":"Guwamu","level":"kelurahan"},{"code":"94.05.05.2009","name":"Kumasingga","level":"kelurahan"}]