[{"code":"75.01.19.2001","name":"Tabongo Timur","level":"kelurahan"},{"code":"75.01.19.2002","name":"Tabongo Barat","level":"kelurahan"},{"code":"75.01.19.2003","name":"Limehe Barat","level":"kelurahan"},{"code":"75.01.19.2004","name":"Limehe Timur","level":"kelurahan"},{"code":"75.01.19.2005","name":"Ilomangga","level":"kelurahan"},{"code":"75.01.19.2006","name":"Motinelo","level":"kelurahan"},{"code":"75.01.19.2007","name":"Moahudu","level":"kelurahan"},{"code":"75.01.19.2008","name":"Teratai","level":"kelurahan"},{"code":"75.01.19.2009","name":"Limehu","level":"kelurahan"}]