[{"code":"73.04.11.2001","name":"Pao","level":"kelurahan"},{"code":"73.04.11.2002","name":"Bontorappo","level":"kelurahan"},{"code":"73.04.11.2003","name":"Tarowang","level":"kelurahan"},{"code":"73.04.11.2004","name":"Allu Tarowang","level":"kelurahan"},{"code":"73.04.11.2005","name":"Balangbaru","level":"kelurahan"},{"code":"73.04.11.2006","name":"Balangloe Tarowang","level":"kelurahan"},{"code":"73.04.11.2007","name":"Bonto Ujung","level":"kelurahan"},{"code":"73.04.11.2008","name":"Tino","level":"kelurahan"}]